<?xml version="1.0" encoding="UTF-8"?>
<!-- generated: 2014-09-26T15:07:06-07:00 -->
<!-- generated by: juve [??] -->
<adag xmlns="http://pegasus.isi.edu/schema/DAX" xmlns:xsi="http://www.w3.org/2001/XMLSchema-instance" xsi:schemaLocation="http://pegasus.isi.edu/schema/DAX http://pegasus.isi.edu/schema/dax-2.1.xsd" version="2.1" count="1" index="0" name="test" jobCount="100" fileCount="0" childCount="98">
<!-- part 1: list of all referenced files (may be empty) -->
<!-- part 2: definition of all jobs (at least one) -->
  <job id="ID00000" namespace="CyberShake" name="ZipPSA" version="1.0" runtime="0.70">
    <uses file="PeakVals_FFI_0_1_ID00003.bsa" link="input" register="false" transfer="false" optional="false" type="data" size="216"/>
    <uses file="PeakVals_FFI_0_1_ID00005.bsa" link="input" register="false" transfer="false" optional="false" type="data" size="216"/>
    <uses file="PeakVals_FFI_0_1_ID00007.bsa" link="input" register="false" transfer="false" optional="false" type="data" size="216"/>
    <uses file="PeakVals_FFI_0_1_ID00009.bsa" link="input" register="false" transfer="false" optional="false" type="data" size="216"/>
    <uses file="PeakVals_FFI_0_1_ID00011.bsa" link="input" register="false" transfer="false" optional="false" type="data" size="216"/>
    <uses file="PeakVals_FFI_0_1_ID00013.bsa" link="input" register="false" transfer="false" optional="false" type="data" size="216"/>
    <uses file="PeakVals_FFI_0_1_ID00015.bsa" link="input" register="false" transfer="false" optional="false" type="data" size="216"/>
    <uses file="PeakVals_FFI_0_1_ID00017.bsa" link="input" register="false" transfer="false" optional="false" type="data" size="216"/>
    <uses file="PeakVals_FFI_0_1_ID00019.bsa" link="input" register="false" transfer="false" optional="false" type="data" size="216"/>
    <uses file="PeakVals_FFI_0_1_ID00021.bsa" link="input" register="false" transfer="false" optional="false" type="data" size="216"/>
    <uses file="PeakVals_FFI_0_1_ID00023.bsa" link="input" register="false" transfer="false" optional="false" type="data" size="216"/>
    <uses file="PeakVals_FFI_0_1_ID00025.bsa" link="input" register="false" transfer="false" optional="false" type="data" size="216"/>
    <uses file="PeakVals_FFI_0_1_ID00027.bsa" link="input" register="false" transfer="false" optional="false" type="data" size="216"/>
    <uses file="PeakVals_FFI_0_1_ID00029.bsa" link="input" register="false" transfer="false" optional="false" type="data" size="216"/>
    <uses file="PeakVals_FFI_0_1_ID00031.bsa" link="input" register="false" transfer="false" optional="false" type="data" size="216"/>
    <uses file="PeakVals_FFI_0_1_ID00033.bsa" link="input" register="false" transfer="false" optional="false" type="data" size="216"/>
    <uses file="PeakVals_FFI_0_1_ID00035.bsa" link="input" register="false" transfer="false" optional="false" type="data" size="216"/>
    <uses file="PeakVals_FFI_0_1_ID00037.bsa" link="input" register="false" transfer="false" optional="false" type="data" size="216"/>
    <uses file="PeakVals_FFI_0_1_ID00039.bsa" link="input" register="false" transfer="false" optional="false" type="data" size="216"/>
    <uses file="PeakVals_FFI_0_1_ID00041.bsa" link="input" register="false" transfer="false" optional="false" type="data" size="216"/>
    <uses file="PeakVals_FFI_0_1_ID00043.bsa" link="input" register="false" transfer="false" optional="false" type="data" size="216"/>
    <uses file="PeakVals_FFI_0_1_ID00045.bsa" link="input" register="false" transfer="false" optional="false" type="data" size="216"/>
    <uses file="PeakVals_FFI_0_2_ID00048.bsa" link="input" register="false" transfer="false" optional="false" type="data" size="216"/>
    <uses file="PeakVals_FFI_0_2_ID00050.bsa" link="input" register="false" transfer="false" optional="false" type="data" size="216"/>
    <uses file="PeakVals_FFI_0_2_ID00052.bsa" link="input" register="false" transfer="false" optional="false" type="data" size="216"/>
    <uses file="PeakVals_FFI_0_2_ID00054.bsa" link="input" register="false" transfer="false" optional="false" type="data" size="216"/>
    <uses file="PeakVals_FFI_0_2_ID00056.bsa" link="input" register="false" transfer="false" optional="false" type="data" size="216"/>
    <uses file="PeakVals_FFI_0_2_ID00058.bsa" link="input" register="false" transfer="false" optional="false" type="data" size="216"/>
    <uses file="PeakVals_FFI_0_2_ID00060.bsa" link="input" register="false" transfer="false" optional="false" type="data" size="216"/>
    <uses file="PeakVals_FFI_0_2_ID00062.bsa" link="input" register="false" transfer="false" optional="false" type="data" size="216"/>
    <uses file="PeakVals_FFI_0_2_ID00064.bsa" link="input" register="false" transfer="false" optional="false" type="data" size="216"/>
    <uses file="PeakVals_FFI_0_2_ID00066.bsa" link="input" register="false" transfer="false" optional="false" type="data" size="216"/>
    <uses file="PeakVals_FFI_0_2_ID00068.bsa" link="input" register="false" transfer="false" optional="false" type="data" size="216"/>
    <uses file="PeakVals_FFI_0_2_ID00070.bsa" link="input" register="false" transfer="false" optional="false" type="data" size="216"/>
    <uses file="PeakVals_FFI_0_2_ID00072.bsa" link="input" register="false" transfer="false" optional="false" type="data" size="216"/>
    <uses file="PeakVals_FFI_0_2_ID00074.bsa" link="input" register="false" transfer="false" optional="false" type="data" size="216"/>
    <uses file="PeakVals_FFI_0_2_ID00076.bsa" link="input" register="false" transfer="false" optional="false" type="data" size="216"/>
    <uses file="PeakVals_FFI_0_2_ID00078.bsa" link="input" register="false" transfer="false" optional="false" type="data" size="216"/>
    <uses file="PeakVals_FFI_0_2_ID00080.bsa" link="input" register="false" transfer="false" optional="false" type="data" size="216"/>
    <uses file="PeakVals_FFI_0_2_ID00082.bsa" link="input" register="false" transfer="false" optional="false" type="data" size="216"/>
    <uses file="PeakVals_FFI_0_2_ID00084.bsa" link="input" register="false" transfer="false" optional="false" type="data" size="216"/>
    <uses file="PeakVals_FFI_0_2_ID00086.bsa" link="input" register="false" transfer="false" optional="false" type="data" size="216"/>
    <uses file="PeakVals_FFI_0_2_ID00088.bsa" link="input" register="false" transfer="false" optional="false" type="data" size="216"/>
    <uses file="PeakVals_FFI_0_2_ID00090.bsa" link="input" register="false" transfer="false" optional="false" type="data" size="216"/>
    <uses file="PeakVals_FFI_0_2_ID00092.bsa" link="input" register="false" transfer="false" optional="false" type="data" size="216"/>
    <uses file="PeakVals_FFI_0_2_ID00094.bsa" link="input" register="false" transfer="false" optional="false" type="data" size="216"/>
    <uses file="PeakVals_FFI_0_2_ID00096.bsa" link="input" register="false" transfer="false" optional="false" type="data" size="216"/>
    <uses file="PeakVals_FFI_0_2_ID00098.bsa" link="input" register="false" transfer="false" optional="false" type="data" size="216"/>
    <uses file="Cybershake_PSA.zip" link="output" register="true" transfer="true" optional="false" type="data" size="1952"/>
  </job>
  <job id="ID00001" namespace="CyberShake" name="ZipSeis" version="1.0" runtime="0.64">
    <uses file="Seismogram_FFI_0_1_ID00003.grm" link="input" register="false" transfer="false" optional="false" type="data" size="24000"/>
    <uses file="Seismogram_FFI_0_1_ID00005.grm" link="input" register="false" transfer="false" optional="false" type="data" size="24000"/>
    <uses file="Seismogram_FFI_0_1_ID00007.grm" link="input" register="false" transfer="false" optional="false" type="data" size="24000"/>
    <uses file="Seismogram_FFI_0_1_ID00009.grm" link="input" register="false" transfer="false" optional="false" type="data" size="24000"/>
    <uses file="Seismogram_FFI_0_1_ID00011.grm" link="input" register="false" transfer="false" optional="false" type="data" size="24000"/>
    <uses file="Seismogram_FFI_0_1_ID00013.grm" link="input" register="false" transfer="false" optional="false" type="data" size="24000"/>
    <uses file="Seismogram_FFI_0_1_ID00015.grm" link="input" register="false" transfer="false" optional="false" type="data" size="24000"/>
    <uses file="Seismogram_FFI_0_1_ID00017.grm" link="input" register="false" transfer="false" optional="false" type="data" size="24000"/>
    <uses file="Seismogram_FFI_0_1_ID00019.grm" link="input" register="false" transfer="false" optional="false" type="data" size="24000"/>
    <uses file="Seismogram_FFI_0_1_ID00021.grm" link="input" register="false" transfer="false" optional="false" type="data" size="24000"/>
    <uses file="Seismogram_FFI_0_1_ID00023.grm" link="input" register="false" transfer="false" optional="false" type="data" size="24000"/>
    <uses file="Seismogram_FFI_0_1_ID00025.grm" link="input" register="false" transfer="false" optional="false" type="data" size="24000"/>
    <uses file="Seismogram_FFI_0_1_ID00027.grm" link="input" register="false" transfer="false" optional="false" type="data" size="24000"/>
    <uses file="Seismogram_FFI_0_1_ID00029.grm" link="input" register="false" transfer="false" optional="false" type="data" size="24000"/>
    <uses file="Seismogram_FFI_0_1_ID00031.grm" link="input" register="false" transfer="false" optional="false" type="data" size="24000"/>
    <uses file="Seismogram_FFI_0_1_ID00033.grm" link="input" register="false" transfer="false" optional="false" type="data" size="24000"/>
    <uses file="Seismogram_FFI_0_1_ID00035.grm" link="input" register="false" transfer="false" optional="false" type="data" size="24000"/>
    <uses file="Seismogram_FFI_0_1_ID00037.grm" link="input" register="false" transfer="false" optional="false" type="data" size="24000"/>
    <uses file="Seismogram_FFI_0_1_ID00039.grm" link="input" register="false" transfer="false" optional="false" type="data" size="24000"/>
    <uses file="Seismogram_FFI_0_1_ID00041.grm" link="input" register="false" transfer="false" optional="false" type="data" size="24000"/>
    <uses file="Seismogram_FFI_0_1_ID00043.grm" link="input" register="false" transfer="false" optional="false" type="data" size="24000"/>
    <uses file="Seismogram_FFI_0_1_ID00045.grm" link="input" register="false" transfer="false" optional="false" type="data" size="24000"/>
    <uses file="Seismogram_FFI_0_2_ID00048.grm" link="input" register="false" transfer="false" optional="false" type="data" size="24000"/>
    <uses file="Seismogram_FFI_0_2_ID00050.grm" link="input" register="false" transfer="false" optional="false" type="data" size="24000"/>
    <uses file="Seismogram_FFI_0_2_ID00052.grm" link="input" register="false" transfer="false" optional="false" type="data" size="24000"/>
    <uses file="Seismogram_FFI_0_2_ID00054.grm" link="input" register="false" transfer="false" optional="false" type="data" size="24000"/>
    <uses file="Seismogram_FFI_0_2_ID00056.grm" link="input" register="false" transfer="false" optional="false" type="data" size="24000"/>
    <uses file="Seismogram_FFI_0_2_ID00058.grm" link="input" register="false" transfer="false" optional="false" type="data" size="24000"/>
    <uses file="Seismogram_FFI_0_2_ID00060.grm" link="input" register="false" transfer="false" optional="false" type="data" size="24000"/>
    <uses file="Seismogram_FFI_0_2_ID00062.grm" link="input" register="false" transfer="false" optional="false" type="data" size="24000"/>
    <uses file="Seismogram_FFI_0_2_ID00064.grm" link="input" register="false" transfer="false" optional="false" type="data" size="24000"/>
    <uses file="Seismogram_FFI_0_2_ID00066.grm" link="input" register="false" transfer="false" optional="false" type="data" size="24000"/>
    <uses file="Seismogram_FFI_0_2_ID00068.grm" link="input" register="false" transfer="false" optional="false" type="data" size="24000"/>
    <uses file="Seismogram_FFI_0_2_ID00070.grm" link="input" register="false" transfer="false" optional="false" type="data" size="24000"/>
    <uses file="Seismogram_FFI_0_2_ID00072.grm" link="input" register="false" transfer="false" optional="false" type="data" size="24000"/>
    <uses file="Seismogram_FFI_0_2_ID00074.grm" link="input" register="false" transfer="false" optional="false" type="data" size="24000"/>
    <uses file="Seismogram_FFI_0_2_ID00076.grm" link="input" register="false" transfer="false" optional="false" type="data" size="24000"/>
    <uses file="Seismogram_FFI_0_2_ID00078.grm" link="input" register="false" transfer="false" optional="false" type="data" size="24000"/>
    <uses file="Seismogram_FFI_0_2_ID00080.grm" link="input" register="false" transfer="false" optional="false" type="data" size="24000"/>
    <uses file="Seismogram_FFI_0_2_ID00082.grm" link="input" register="false" transfer="false" optional="false" type="data" size="24000"/>
    <uses file="Seismogram_FFI_0_2_ID00084.grm" link="input" register="false" transfer="false" optional="false" type="data" size="24000"/>
    <uses file="Seismogram_FFI_0_2_ID00086.grm" link="input" register="false" transfer="false" optional="false" type="data" size="24000"/>
    <uses file="Seismogram_FFI_0_2_ID00088.grm" link="input" register="false" transfer="false" optional="false" type="data" size="24000"/>
    <uses file="Seismogram_FFI_0_2_ID00090.grm" link="input" register="false" transfer="false" optional="false" type="data" size="24000"/>
    <uses file="Seismogram_FFI_0_2_ID00092.grm" link="input" register="false" transfer="false" optional="false" type="data" size="24000"/>
    <uses file="Seismogram_FFI_0_2_ID00094.grm" link="input" register="false" transfer="false" optional="false" type="data" size="24000"/>
    <uses file="Seismogram_FFI_0_2_ID00096.grm" link="input" register="false" transfer="false" optional="false" type="data" size="24000"/>
    <uses file="Seismogram_FFI_0_2_ID00098.grm" link="input" register="false" transfer="false" optional="false" type="data" size="24000"/>
    <uses file="Cybershake_Seismograms.zip" link="output" register="true" transfer="true" optional="false" type="data" size="147070"/>
  </job>
  <job id="ID00002" namespace="CyberShake" name="ExtractSGT" version="1.0" runtime="164.74">
    <uses file="FFI_0_1_fx.sgt" link="input" register="true" transfer="true" optional="false" type="data" size="20250656767"/>
    <uses file="FFI_0_1_fy.sgt" link="input" register="true" transfer="true" optional="false" type="data" size="20250656767"/>
    <uses file="FFI_0_1_subfx.sgt" link="output" register="false" transfer="false" optional="false" type="data" size="307881638"/>
    <uses file="FFI_0_1_subfy.sgt" link="output" register="false" transfer="false" optional="false" type="data" size="307881638"/>
    <uses file="FFI_0_1_txt.variation-s03550-h00041" link="input" register="true" transfer="true" optional="false" type="data" size="2192732"/>
  </job>
  <job id="ID00003" namespace="CyberShake" name="SeismogramSynthesis" version="1.0" runtime="37.67">
    <uses file="FFI_0_1_txt.variation-s02494-h05895" link="input" register="true" transfer="true" optional="false" type="data" size="5267432"/>
    <uses file="FFI_0_1_subfx.sgt" link="input" register="false" transfer="false" optional="false" type="data" size="307881638"/>
    <uses file="FFI_0_1_subfy.sgt" link="input" register="false" transfer="false" optional="false" type="data" size="307881638"/>
    <uses file="Seismogram_FFI_0_1_ID00003.grm" link="output" register="false" transfer="false" optional="false" type="data" size="24000"/>
  </job>
  <job id="ID00004" namespace="CyberShake" name="PeakValCalcOkaya" version="1.0" runtime="1.05">
    <uses file="Seismogram_FFI_0_1_ID00003.grm" link="input" register="false" transfer="false" optional="false" type="data" size="24000"/>
    <uses file="PeakVals_FFI_0_1_ID00003.bsa" link="output" register="false" transfer="false" optional="false" type="data" size="216"/>
  </job>
  <job id="ID00005" namespace="CyberShake" name="SeismogramSynthesis" version="1.0" runtime="59.03">
    <uses file="FFI_0_1_txt.variation-s09668-h06261" link="input" register="true" transfer="true" optional="false" type="data" size="2415375"/>
    <uses file="FFI_0_1_subfx.sgt" link="input" register="false" transfer="false" optional="false" type="data" size="287437392"/>
    <uses file="FFI_0_1_subfy.sgt" link="input" register="false" transfer="false" optional="false" type="data" size="287437392"/>
    <uses file="Seismogram_FFI_0_1_ID00005.grm" link="output" register="false" transfer="false" optional="false" type="data" size="24000"/>
  </job>
  <job id="ID00006" namespace="CyberShake" name="PeakValCalcOkaya" version="1.0" runtime="0.57">
    <uses file="Seismogram_FFI_0_1_ID00005.grm" link="input" register="false" transfer="false" optional="false" type="data" size="24000"/>
    <uses file="PeakVals_FFI_0_1_ID00005.bsa" link="output" register="false" transfer="false" optional="false" type="data" size="216"/>
  </job>
  <job id="ID00007" namespace="CyberShake" name="SeismogramSynthesis" version="1.0" runtime="39.91">
    <uses file="FFI_0_1_txt.variation-s06296-h05599" link="input" register="true" transfer="true" optional="false" type="data" size="4171486"/>
    <uses file="FFI_0_1_subfx.sgt" link="input" register="false" transfer="false" optional="false" type="data" size="147217225"/>
    <uses file="FFI_0_1_subfy.sgt" link="input" register="false" transfer="false" optional="false" type="data" size="147217225"/>
    <uses file="Seismogram_FFI_0_1_ID00007.grm" link="output" register="false" transfer="false" optional="false" type="data" size="24000"/>
  </job>
  <job id="ID00008" namespace="CyberShake" name="PeakValCalcOkaya" version="1.0" runtime="1.17">
    <uses file="Seismogram_FFI_0_1_ID00007.grm" link="input" register="false" transfer="false" optional="false" type="data" size="24000"/>
    <uses file="PeakVals_FFI_0_1_ID00007.bsa" link="output" register="false" transfer="false" optional="false" type="data" size="216"/>
  </job>
  <job id="ID00009" namespace="CyberShake" name="SeismogramSynthesis" version="1.0" runtime="36.85">
    <uses file="FFI_0_1_txt.variation-s01870-h04205" link="input" register="true" transfer="true" optional="false" type="data" size="5490684"/>
    <uses file="FFI_0_1_subfx.sgt" link="input" register="false" transfer="false" optional="false" type="data" size="315681036"/>
    <uses file="FFI_0_1_subfy.sgt" link="input" register="false" transfer="false" optional="false" type="data" size="315681036"/>
    <uses file="Seismogram_FFI_0_1_ID00009.grm" link="output" register="false" transfer="false" optional="false" type="data" size="24000"/>
  </job>
  <job id="ID00010" namespace="CyberShake" name="PeakValCalcOkaya" version="1.0" runtime="1.61">
    <uses file="Seismogram_FFI_0_1_ID00009.grm" link="input" register="false" transfer="false" optional="false" type="data" size="24000"/>
    <uses file="PeakVals_FFI_0_1_ID00009.bsa" link="output" register="false" transfer="false" optional="false" type="data" size="216"/>
  </job>
  <job id="ID00011" namespace="CyberShake" name="SeismogramSynthesis" version="1.0" runtime="23.88">
    <uses file="FFI_0_1_txt.variation-s03440-h06995" link="input" register="true" transfer="true" optional="false" type="data" size="1888540"/>
    <uses file="FFI_0_1_subfx.sgt" link="input" register="false" transfer="false" optional="false" type="data" size="193999876"/>
    <uses file="FFI_0_1_subfy.sgt" link="input" register="false" transfer="false" optional="false" type="data" size="193999876"/>
    <uses file="Seismogram_FFI_0_1_ID00011.grm" link="output" register="false" transfer="false" optional="false" type="data" size="24000"/>
  </job>
  <job id="ID00012" namespace="CyberShake" name="PeakValCalcOkaya" version="1.0" runtime="0.95">
    <uses file="Seismogram_FFI_0_1_ID00011.grm" link="input" register="false" transfer="false" optional="false" type="data" size="24000"/>
    <uses file="PeakVals_FFI_0_1_ID00011.bsa" link="output" register="false" transfer="false" optional="false" type="data" size="216"/>
  </job>
  <job id="ID00013" namespace="CyberShake" name="SeismogramSynthesis" version="1.0" runtime="55.30">
    <uses file="FFI_0_1_txt.variation-s05578-h04657" link="input" register="true" transfer="true" optional="false" type="data" size="2971945"/>
    <uses file="FFI_0_1_subfx.sgt" link="input" register="false" transfer="false" optional="false" type="data" size="212824116"/>
    <uses file="FFI_0_1_subfy.sgt" link="input" register="false" transfer="false" optional="false" type="data" size="212824116"/>
    <uses file="Seismogram_FFI_0_1_ID00013.grm" link="output" register="false" transfer="false" optional="false" type="data" size="24000"/>
  </job>
  <job id="ID00014" namespace="CyberShake" name="PeakValCalcOkaya" version="1.0" runtime="1.02">
    <uses file="Seismogram_FFI_0_1_ID00013.grm" link="input" register="false" transfer="false" optional="false" type="data" size="24000"/>
    <uses file="PeakVals_FFI_0_1_ID00013.bsa" link="output" register="false" transfer="false" optional="false" type="data" size="216"/>
  </job>
  <job id="ID00015" namespace="CyberShake" name="SeismogramSynthesis" version="1.0" runtime="56.56">
    <uses file="FFI_0_1_txt.variation-s09609-h01909" link="input" register="true" transfer="true" optional="false" type="data" size="2091402"/>
    <uses file="FFI_0_1_subfx.sgt" link="input" register="false" transfer="false" optional="false" type="data" size="133876564"/>
    <uses file="FFI_0_1_subfy.sgt" link="input" register="false" transfer="false" optional="false" type="data" size="133876564"/>
    <uses file="Seismogram_FFI_0_1_ID00015.grm" link="output" register="false" transfer="false" optional="false" type="data" size="24000"/>
  </job>
  <job id="ID00016" namespace="CyberShake" name="PeakValCalcOkaya" version="1.0" runtime="0.66">
    <uses file="Seismogram_FFI_0_1_ID00015.grm" link="input" register="false" transfer="false" optional="false" type="data" size="24000"/>
    <uses file="PeakVals_FFI_0_1_ID00015.bsa" link="output" register="false" transfer="false" optional="false" type="data" size="216"/>
  </job>
  <job id="ID00017" namespace="CyberShake" name="SeismogramSynthesis" version="1.0" runtime="29.84">
    <uses file="FFI_0_1_txt.variation-s03071-h00361" link="input" register="true" transfer="true" optional="false" type="data" size="2964001"/>
    <uses file="FFI_0_1_subfx.sgt" link="input" register="false" transfer="false" optional="false" type="data" size="306221588"/>
    <uses file="FFI_0_1_subfy.sgt" link="input" register="false" transfer="false" optional="false" type="data" size="306221588"/>
    <uses file="Seismogram_FFI_0_1_ID00017.grm" link="output" register="false" transfer="false" optional="false" type="data" size="24000"/>
  </job>
  <job id="ID00018" namespace="CyberShake" name="PeakValCalcOkaya" version="1.0" runtime="0.57">
    <uses file="Seismogram_FFI_0_1_ID00017.grm" link="input" register="false" transfer="false" optional="false" type="data" size="24000"/>
    <uses file="PeakVals_FFI_0_1_ID00017.bsa" link="output" register="false" transfer="false" optional="false" type="data" size="216"/>
  </job>
  <job id="ID00019" namespace="CyberShake" name="SeismogramSynthesis" version="1.0" runtime="29.85">
    <uses file="FFI_0_1_txt.variation-s08788-h01100" link="input" register="true" transfer="true" optional="false" type="data" size="4257166"/>
    <uses file="FFI_0_1_subfx.sgt" link="input" register="false" transfer="false" optional="false" type="data" size="314014042"/>
    <uses file="FFI_0_1_subfy.sgt" link="input" register="false" transfer="false" optional="false" type="data" size="314014042"/>
    <uses file="Seismogram_FFI_0_1_ID00019.grm" link="output" register="false" transfer="false" optional="false" type="data" size="24000"/>
  </job>
  <job id="ID00020" namespace="CyberShake" name="PeakValCalcOkaya" version="1.0" runtime="1.05">
    <uses file="Seismogram_FFI_0_1_ID00019.grm" link="input" register="false" transfer="false" optional="false" type="data" size="24000"/>
    <uses file="PeakVals_FFI_0_1_ID00019.bsa" link="output" register="false" transfer="false" optional="false" type="data" size="216"/>
  </job>
  <job id="ID00021" namespace="CyberShake" name="SeismogramSynthesis" version="1.0" runtime="46.27">
    <uses file="FFI_0_1_txt.variation-s09570-h03346" link="input" register="true" transfer="true" optional="false" type="data" size="4162459"/>
    <uses file="FFI_0_1_subfx.sgt" link="input" register="false" transfer="false" optional="false" type="data" size="177639089"/>
    <uses file="FFI_0_1_subfy.sgt" link="input" register="false" transfer="false" optional="false" type="data" size="177639089"/>
    <uses file="Seismogram_FFI_0_1_ID00021.grm" link="output" register="false" transfer="false" optional="false" type="data" size="24000"/>
  </job>
  <job id="ID00022" namespace="CyberShake" name="PeakValCalcOkaya" version="1.0" runtime="0.84">
    <uses file="Seismogram_FFI_0_1_ID00021.grm" link="input" register="false" transfer="false" optional="false" type="data" size="24000"/>
    <uses file="PeakVals_FFI_0_1_ID00021.bsa" link="output" register="false" transfer="false" optional="false" type="data" size="216"/>
  </job>
  <job id="ID00023" namespace="CyberShake" name="SeismogramSynthesis" version="1.0" runtime="35.34">
    <uses file="FFI_0_1_txt.variation-s06016-h03616" link="input" register="true" transfer="true" optional="false" type="data" size="3241768"/>
    <uses file="FFI_0_1_subfx.sgt" link="input" register="false" transfer="false" optional="false" type="data" size="141554394"/>
    <uses file="FFI_0_1_subfy.sgt" link="input" register="false" transfer="false" optional="false" type="data" size="141554394"/>
    <uses file="Seismogram_FFI_0_1_ID00023.grm" link="output" register="false" transfer="false" optional="false" type="data" size="24000"/>
  </job>
  <job id="ID00024" namespace="CyberShake" name="PeakValCalcOkaya" version="1.0" runtime="0.92">
    <uses file="Seismogram_FFI_0_1_ID00023.grm" link="input" register="false" transfer="false" optional="false" type="data" size="24000"/>
    <uses file="PeakVals_FFI_0_1_ID00023.bsa" link="output" register="false" transfer="false" optional="false" type="data" size="216"/>
  </job>
  <job id="ID00025" namespace="CyberShake" name="SeismogramSynthesis" version="1.0" runtime="24.86">
    <uses file="FFI_0_1_txt.variation-s05007-h01024" link="input" register="true" transfer="true" optional="false" type="data" size="4024988"/>
    <uses file="FFI_0_1_subfx.sgt" link="input" register="false" transfer="false" optional="false" type="data" size="278985753"/>
    <uses file="FFI_0_1_subfy.sgt" link="input" register="false" transfer="false" optional="false" type="data" size="278985753"/>
    <uses file="Seismogram_FFI_0_1_ID00025.grm" link="output" register="false" transfer="false" optional="false" type="data" size="24000"/>
  </job>
  <job id="ID00026" namespace="CyberShake" name="PeakValCalcOkaya" version="1.0" runtime="1.39">
    <uses file="Seismogram_FFI_0_1_ID00025.grm" link="input" register="false" transfer="false" optional="false" type="data" size="24000"/>
    <uses file="PeakVals_FFI_0_1_ID00025.bsa" link="output" register="false" transfer="false" optional="false" type="data" size="216"/>
  </job>
  <job id="ID00027" namespace="CyberShake" name="SeismogramSynthesis" version="1.0" runtime="61.38">
    <uses file="FFI_0_1_txt.variation-s04129-h09001" link="input" register="true" transfer="true" optional="false" type="data" size="4715480"/>
    <uses file="FFI_0_1_subfx.sgt" link="input" register="false" transfer="false" optional="false" type="data" size="213028164"/>
    <uses file="FFI_0_1_subfy.sgt" link="input" register="false" transfer="false" optional="false" type="data" size="213028164"/>
    <uses file="Seismogram_FFI_0_1_ID00027.grm" link="output" register="false" transfer="false" optional="false" type="data" size="24000"/>
  </job>
  <job id="ID00028" namespace="CyberShake" name="PeakValCalcOkaya" version="1.0" runtime="1.47">
    <uses file="Seismogram_FFI_0_1_ID00027.grm" link="input" register="false" transfer="false" optional="false" type="data" size="24000"/>
    <uses file="PeakVals_FFI_0_1_ID00027.bsa" link="output" register="false" transfer="false" optional="false" type="data" size="216"/>
  </job>
  <job id="ID00029" namespace="CyberShake" name="SeismogramSynthesis" version="1.0" runtime="49.51">
    <uses file="FFI_0_1_txt.variation-s00793-h02126" link="input" register="true" transfer="true" optional="false" type="data" size="4179599"/>
    <uses file="FFI_0_1_subfx.sgt" link="input" register="false" transfer="false" optional="false" type="data" size="281750955"/>
    <uses file="FFI_0_1_subfy.sgt" link="input" register="false" transfer="false" optional="false" type="data" size="281750955"/>
    <uses file="Seismogram_FFI_0_1_ID00029.grm" link="output" register="false" transfer="false" optional="false" type="data" size="24000"/>
  </job>
  <job id="ID00030" namespace="CyberShake" name="PeakValCalcOkaya" version="1.0" runtime="0.71">
    <uses file="Seismogram_FFI_0_1_ID00029.grm" link="input" register="false" transfer="false" optional="false" type="data" size="24000"/>
    <uses file="PeakVals_FFI_0_1_ID00029.bsa" link="output" register="false" transfer="false" optional="false" type="data" size="216"/>
  </job>
  <job id="ID00031" namespace="CyberShake" name="SeismogramSynthesis" version="1.0" runtime="33.07">
    <uses file="FFI_0_1_txt.variation-s07367-h01561" link="input" register="true" transfer="true" optional="false" type="data" size="2575428"/>
    <uses file="FFI_0_1_subfx.sgt" link="input" register="false" transfer="false" optional="false" type="data" size="187872381"/>
    <uses file="FFI_0_1_subfy.sgt" link="input" register="false" transfer="false" optional="false" type="data" size="187872381"/>
    <uses file="Seismogram_FFI_0_1_ID00031.grm" link="output" register="false" transfer="false" optional="false" type="data" size="24000"/>
  </job>
  <job id="ID00032" namespace="CyberShake" name="PeakValCalcOkaya" version="1.0" runtime="0.70">
    <uses file="Seismogram_FFI_0_1_ID00031.grm" link="input" register="false" transfer="false" optional="false" type="data" size="24000"/>
    <uses file="PeakVals_FFI_0_1_ID00031.bsa" link="output" register="false" transfer="false" optional="false" type="data" size="216"/>
  </job>
  <job id="ID00033" namespace="CyberShake" name="SeismogramSynthesis" version="1.0" runtime="35.24">
    <uses file="FFI_0_1_txt.variation-s03498-h09280" link="input" register="true" transfer="true" optional="false" type="data" size="5443004"/>
    <uses file="FFI_0_1_subfx.sgt" link="input" register="false" transfer="false" optional="false" type="data" size="302867396"/>
    <uses file="FFI_0_1_subfy.sgt" link="input" register="false" transfer="false" optional="false" type="data" size="302867396"/>
    <uses file="Seismogram_FFI_0_1_ID00033.grm" link="output" register="false" transfer="false" optional="false" type="data" size="24000"/>
  </job>
  <job id="ID00034" namespace="CyberShake" name="PeakValCalcOkaya" version="1.0" runtime="1.48">
    <uses file="Seismogram_FFI_0_1_ID00033.grm" link="input" register="false" transfer="false" optional="false" type="data" size="24000"/>
    <uses file="PeakVals_FFI_0_1_ID00033.bsa" link="output" register="false" transfer="false" optional="false" type="data" size="216"/>
  </job>
  <job id="ID00035" namespace="CyberShake" name="SeismogramSynthesis" version="1.0" runtime="30.35">
    <uses file="FFI_0_1_txt.variation-s01650-h06220" link="input" register="true" transfer="true" optional="false" type="data" size="3555858"/>
    <uses file="FFI_0_1_subfx.sgt" link="input" register="false" transfer="false" optional="false" type="data" size="313048862"/>
    <uses file="FFI_0_1_subfy.sgt" link="input" register="false" transfer="false" optional="false" type="data" size="313048862"/>
    <uses file="Seismogram_FFI_0_1_ID00035.grm" link="output" register="false" transfer="false" optional="false" type="data" size="24000"/>
  </job>
  <job id="ID00036" namespace="CyberShake" name="PeakValCalcOkaya" version="1.0" runtime="0.98">
    <uses file="Seismogram_FFI_0_1_ID00035.grm" link="input" register="false" transfer="false" optional="false" type="data" size="24000"/>
    <uses file="PeakVals_FFI_0_1_ID00035.bsa" link="output" register="false" transfer="false" optional="false" type="data" size="216"/>
  </job>
  <job id="ID00037" namespace="CyberShake" name="SeismogramSynthesis" version="1.0" runtime="36.84">
    <uses file="FFI_0_1_txt.variation-s08237-h06632" link="input" register="true" transfer="true" optional="false" type="data" size="3182035"/>
    <uses file="FFI_0_1_subfx.sgt" link="input" register="false" transfer="false" optional="false" type="data" size="261405380"/>
    <uses file="FFI_0_1_subfy.sgt" link="input" register="false" transfer="false" optional="false" type="data" size="261405380"/>
    <uses file="Seismogram_FFI_0_1_ID00037.grm" link="output" register="false" transfer="false" optional="false" type="data" size="24000"/>
  </job>
  <job id="ID00038" namespace="CyberShake" name="PeakValCalcOkaya" version="1.0" runtime="1.41">
    <uses file="Seismogram_FFI_0_1_ID00037.grm" link="input" register="false" transfer="false" optional="false" type="data" size="24000"/>
    <uses file="PeakVals_FFI_0_1_ID00037.bsa" link="output" register="false" transfer="false" optional="false" type="data" size="216"/>
  </job>
  <job id="ID00039" namespace="CyberShake" name="SeismogramSynthesis" version="1.0" runtime="46.39">
    <uses file="FFI_0_1_txt.variation-s02408-h09354" link="input" register="true" transfer="true" optional="false" type="data" size="3512409"/>
    <uses file="FFI_0_1_subfx.sgt" link="input" register="false" transfer="false" optional="false" type="data" size="138089347"/>
    <uses file="FFI_0_1_subfy.sgt" link="input" register="false" transfer="false" optional="false" type="data" size="138089347"/>
    <uses file="Seismogram_FFI_0_1_ID00039.grm" link="output" register="false" transfer="false" optional="false" type="data" size="24000"/>
  </job>
  <job id="ID00040" namespace="CyberShake" name="PeakValCalcOkaya" version="1.0" runtime="1.43">
    <uses file="Seismogram_FFI_0_1_ID00039.grm" link="input" register="false" transfer="false" optional="false" type="data" size="24000"/>
    <uses file="PeakVals_FFI_0_1_ID00039.bsa" link="output" register="false" transfer="false" optional="false" type="data" size="216"/>
  </job>
  <job id="ID00041" namespace="CyberShake" name="SeismogramSynthesis" version="1.0" runtime="21.72">
    <uses file="FFI_0_1_txt.variation-s06719-h04173" link="input" register="true" transfer="true" optional="false" type="data" size="5247816"/>
    <uses file="FFI_0_1_subfx.sgt" link="input" register="false" transfer="false" optional="false" type="data" size="151338583"/>
    <uses file="FFI_0_1_subfy.sgt" link="input" register="false" transfer="false" optional="false" type="data" size="151338583"/>
    <uses file="Seismogram_FFI_0_1_ID00041.grm" link="output" register="false" transfer="false" optional="false" type="data" size="24000"/>
  </job>
  <job id="ID00042" namespace="CyberShake" name="PeakValCalcOkaya" version="1.0" runtime="1.42">
    <uses file="Seismogram_FFI_0_1_ID00041.grm" link="input" register="false" transfer="false" optional="false" type="data" size="24000"/>
    <uses file="PeakVals_FFI_0_1_ID00041.bsa" link="output" register="false" transfer="false" optional="false" type="data" size="216"/>
  </job>
  <job id="ID00043" namespace="CyberShake" name="SeismogramSynthesis" version="1.0" runtime="36.15">
    <uses file="FFI_0_1_txt.variation-s09265-h09011" link="input" register="true" transfer="true" optional="false" type="data" size="4579645"/>
    <uses file="FFI_0_1_subfx.sgt" link="input" register="false" transfer="false" optional="false" type="data" size="236636655"/>
    <uses file="FFI_0_1_subfy.sgt" link="input" register="false" transfer="false" optional="false" type="data" size="236636655"/>
    <uses file="Seismogram_FFI_0_1_ID00043.grm" link="output" register="false" transfer="false" optional="false" type="data" size="24000"/>
  </job>
  <job id="ID00044" namespace="CyberShake" name="PeakValCalcOkaya" version="1.0" runtime="0.61">
    <uses file="Seismogram_FFI_0_1_ID00043.grm" link="input" register="false" transfer="false" optional="false" type="data" size="24000"/>
    <uses file="PeakVals_FFI_0_1_ID00043.bsa" link="output" register="false" transfer="false" optional="false" type="data" size="216"/>
  </job>
  <job id="ID00045" namespace="CyberShake" name="SeismogramSynthesis" version="1.0" runtime="50.93">
    <uses file="FFI_0_1_txt.variation-s03550-h00041" link="input" register="true" transfer="true" optional="false" type="data" size="2192732"/>
    <uses file="FFI_0_1_subfx.sgt" link="input" register="false" transfer="false" optional="false" type="data" size="250309182"/>
    <uses file="FFI_0_1_subfy.sgt" link="input" register="false" transfer="false" optional="false" type="data" size="250309182"/>
    <uses file="Seismogram_FFI_0_1_ID00045.grm" link="output" register="false" transfer="false" optional="false" type="data" size="24000"/>
  </job>
  <job id="ID00046" namespace="CyberShake" name="PeakValCalcOkaya" version="1.0" runtime="0.80">
    <uses file="Seismogram_FFI_0_1_ID00045.grm" link="input" register="false" transfer="false" optional="false" type="data" size="24000"/>
    <uses file="PeakVals_FFI_0_1_ID00045.bsa" link="output" register="false" transfer="false" optional="false" type="data" size="216"/>
  </job>
  <job id="ID00047" namespace="CyberShake" name="ExtractSGT" version="1.0" runtime="90.75">
    <uses file="FFI_0_2_fx.sgt" link="input" register="true" transfer="true" optional="false" type="data" size="20516952694"/>
    <uses file="FFI_0_2_fy.sgt" link="input" register="true" transfer="true" optional="false" type="data" size="20516952694"/>
    <uses file="FFI_0_2_subfx.sgt" link="output" register="false" transfer="false" optional="false" type="data" size="266173011"/>
    <uses file="FFI_0_2_subfy.sgt" link="output" register="false" transfer="false" optional="false" type="data" size="266173011"/>
    <uses file="FFI_0_2_txt.variation-s00186-h01843" link="input" register="true" transfer="true" optional="false" type="data" size="2326255"/>
  </job>
  <job id="ID00048" namespace="CyberShake" name="SeismogramSynthesis" version="1.0" runtime="64.00">
    <uses file="FFI_0_2_txt.variation-s01884-h03415" link="input" register="true" transfer="true" optional="false" type="data" size="3875934"/>
    <uses file="FFI_0_2_subfx.sgt" link="input" register="false" transfer="false" optional="false" type="data" size="266173011"/>
    <uses file="FFI_0_2_subfy.sgt" link="input" register="false" transfer="false" optional="false" type="data" size="266173011"/>
    <uses file="Seismogram_FFI_0_2_ID00048.grm" link="output" register="false" transfer="false" optional="false" type="data" size="24000"/>
  </job>
  <job id="ID00049" namespace="CyberShake" name="PeakValCalcOkaya" version="1.0" runtime="1.00">
    <uses file="Seismogram_FFI_0_2_ID00048.grm" link="input" register="false" transfer="false" optional="false" type="data" size="24000"/>
    <uses file="PeakVals_FFI_0_2_ID00048.bsa" link="output" register="false" transfer="false" optional="false" type="data" size="216"/>
  </job>
  <job id="ID00050" namespace="CyberShake" name="SeismogramSynthesis" version="1.0" runtime="57.66">
    <uses file="FFI_0_2_txt.variation-s03613-h02723" link="input" register="true" transfer="true" optional="false" type="data" size="2676948"/>
    <uses file="FFI_0_2_subfx.sgt" link="input" register="false" transfer="false" optional="false" type="data" size="301445733"/>
    <uses file="FFI_0_2_subfy.sgt" link="input" register="false" transfer="false" optional="false" type="data" size="301445733"/>
    <uses file="Seismogram_FFI_0_2_ID00050.grm" link="output" register="false" transfer="false" optional="false" type="data" size="24000"/>
  </job>
  <job id="ID00051" namespace="CyberShake" name="PeakValCalcOkaya" version="1.0" runtime="1.14">
    <uses file="Seismogram_FFI_0_2_ID00050.grm" link="input" register="false" transfer="false" optional="false" type="data" size="24000"/>
    <uses file="PeakVals_FFI_0_2_ID00050.bsa" link="output" register="false" transfer="false" optional="false" type="data" size="216"/>
  </job>
  <job id="ID00052" namespace="CyberShake" name="SeismogramSynthesis" version="1.0" runtime="43.33">
    <uses file="FFI_0_2_txt.variation-s09973-h01755" link="input" register="true" transfer="true" optional="false" type="data" size="3870422"/>
    <uses file="FFI_0_2_subfx.sgt" link="input" register="false" transfer="false" optional="false" type="data" size="117640244"/>
    <uses file="FFI_0_2_subfy.sgt" link="input" register="false" transfer="false" optional="false" type="data" size="117640244"/>
    <uses file="Seismogram_FFI_0_2_ID00052.grm" link="output" register="false" transfer="false" optional="false" type="data" size="24000"/>
  </job>
  <job id="ID00053" namespace="CyberShake" name="PeakValCalcOkaya" version="1.0" runtime="0.95">
    <uses file="Seismogram_FFI_0_2_ID00052.grm" link="input" register="false" transfer="false" optional="false" type="data" size="24000"/>
    <uses file="PeakVals_FFI_0_2_ID00052.bsa" link="output" register="false" transfer="false" optional="false" type="data" size="216"/>
  </job>
  <job id="ID00054" namespace="CyberShake" name="SeismogramSynthesis" version="1.0" runtime="50.55">
    <uses file="FFI_0_2_txt.variation-s00853-h01852" link="input" register="true" transfer="true" optional="false" type="data" size="5324584"/>
    <uses file="FFI_0_2_subfx.sgt" link="input" register="false" transfer="false" optional="false" type="data" size="254691701"/>
    <uses file="FFI_0_2_subfy.sgt" link="input" register="false" transfer="false" optional="false" type="data" size="254691701"/>
    <uses file="Seismogram_FFI_0_2_ID00054.grm" link="output" register="false" transfer="false" optional="false" type="data" size="24000"/>
  </job>
  <job id="ID00055" namespace="CyberShake" name="PeakValCalcOkaya" version="1.0" runtime="1.32">
    <uses file="Seismogram_FFI_0_2_ID00054.grm" link="input" register="false" transfer="false" optional="false" type="data" size="24000"/>
    <uses file="PeakVals_FFI_0_2_ID00054.bsa" link="output" register="false" transfer="false" optional="false" type="data" size="216"/>
  </job>
  <job id="ID00056" namespace="CyberShake" name="SeismogramSynthesis" version="1.0" runtime="35.84">
    <uses file="FFI_0_2_txt.variation-s02360-h05632" link="input" register="true" transfer="true" optional="false" type="data" size="4293456"/>
    <uses file="FFI_0_2_subfx.sgt" link="input" register="false" transfer="false" optional="false" type="data" size="270046526"/>
    <uses file="FFI_0_2_subfy.sgt" link="input" register="false" transfer="false" optional="false" type="data" size="270046526"/>
    <uses file="Seismogram_FFI_0_2_ID00056.grm" link="output" register="false" transfer="false" optional="false" type="data" size="24000"/>
  </job>
  <job id="ID00057" namespace="CyberShake" name="PeakValCalcOkaya" version="1.0" runtime="0.77">
    <uses file="Seismogram_FFI_0_2_ID00056.grm" link="input" register="false" transfer="false" optional="false" type="data" size="24000"/>
    <uses file="PeakVals_FFI_0_2_ID00056.bsa" link="output" register="false" transfer="false" optional="false" type="data" size="216"/>
  </job>
  <job id="ID00058" namespace="CyberShake" name="SeismogramSynthesis" version="1.0" runtime="31.79">
    <uses file="FFI_0_2_txt.variation-s02933-h03704" link="input" register="true" transfer="true" optional="false" type="data" size="3415880"/>
    <uses file="FFI_0_2_subfx.sgt" link="input" register="false" transfer="false" optional="false" type="data" size="241889855"/>
    <uses file="FFI_0_2_subfy.sgt" link="input" register="false" transfer="false" optional="false" type="data" size="241889855"/>
    <uses file="Seismogram_FFI_0_2_ID00058.grm" link="output" register="false" transfer="false" optional="false" type="data" size="24000"/>
  </job>
  <job id="ID00059" namespace="CyberShake" name="PeakValCalcOkaya" version="1.0" runtime="1.58">
    <uses file="Seismogram_FFI_0_2_ID00058.grm" link="input" register="false" transfer="false" optional="false" type="data" size="24000"/>
    <uses file="PeakVals_FFI_0_2_ID00058.bsa" link="output" register="false" transfer="false" optional="false" type="data" size="216"/>
  </job>
  <job id="ID00060" namespace="CyberShake" name="SeismogramSynthesis" version="1.0" runtime="39.21">
    <uses file="FFI_0_2_txt.variation-s06320-h02103" link="input" register="true" transfer="true" optional="false" type="data" size="3043801"/>
    <uses file="FFI_0_2_subfx.sgt" link="input" register="false" transfer="false" optional="false" type="data" size="244672362"/>
    <uses file="FFI_0_2_subfy.sgt" link="input" register="false" transfer="false" optional="false" type="data" size="244672362"/>
    <uses file="Seismogram_FFI_0_2_ID00060.grm" link="output" register="false" transfer="false" optional="false" type="data" size="24000"/>
  </job>
  <job id="ID00061" namespace="CyberShake" name="PeakValCalcOkaya" version="1.0" runtime="0.92">
    <uses file="Seismogram_FFI_0_2_ID00060.grm" link="input" register="false" transfer="false" optional="false" type="data" size="24000"/>
    <uses file="PeakVals_FFI_0_2_ID00060.bsa" link="output" register="false" transfer="false" optional="false" type="data" size="216"/>
  </job>
  <job id="ID00062" namespace="CyberShake" name="SeismogramSynthesis" version="1.0" runtime="30.44">
    <uses file="FFI_0_2_txt.variation-s09852-h00079" link="input" register="true" transfer="true" optional="false" type="data" size="4953752"/>
    <uses file="FFI_0_2_subfx.sgt" link="input" register="false" transfer="false" optional="false" type="data" size="327148181"/>
    <uses file="FFI_0_2_subfy.sgt" link="input" register="false" transfer="false" optional="false" type="data" size="327148181"/>
    <uses file="Seismogram_FFI_0_2_ID00062.grm" link="output" register="false" transfer="false" optional="false" type="data" size="24000"/>
  </job>
  <job id="ID00063" namespace="CyberShake" name="PeakValCalcOkaya" version="1.0" runtime="1.47">
    <uses file="Seismogram_FFI_0_2_ID00062.grm" link="input" register="false" transfer="false" optional="false" type="data" size="24000"/>
    <uses file="PeakVals_FFI_0_2_ID00062.bsa" link="output" register="false" transfer="false" optional="false" type="data" size="216"/>
  </job>
  <job id="ID00064" namespace="CyberShake" name="SeismogramSynthesis" version="1.0" runtime="22.29">
    <uses file="FFI_0_2_txt.variation-s01095-h09747" link="input" register="true" transfer="true" optional="false" type="data" size="3047923"/>
    <uses file="FFI_0_2_subfx.sgt" link="input" register="false" transfer="false" optional="false" type="data" size="191784686"/>
    <uses file="FFI_0_2_subfy.sgt" link="input" register="false" transfer="false" optional="false" type="data" size="191784686"/>
    <uses file="Seismogram_FFI_0_2_ID00064.grm" link="output" register="false" transfer="false" optional="false" type="data" size="24000"/>
  </job>
  <job id="ID00065" namespace="CyberShake" name="PeakValCalcOkaya" version="1.0" runtime="0.78">
    <uses file="Seismogram_FFI_0_2_ID00064.grm" link="input" register="false" transfer="false" optional="false" type="data" size="24000"/>
    <uses file="PeakVals_FFI_0_2_ID00064.bsa" link="output" register="false" transfer="false" optional="false" type="data" size="216"/>
  </job>
  <job id="ID00066" namespace="CyberShake" name="SeismogramSynthesis" version="1.0" runtime="29.44">
    <uses file="FFI_0_2_txt.variation-s09369-h08483" link="input" register="true" transfer="true" optional="false" type="data" size="5191492"/>
    <uses file="FFI_0_2_subfx.sgt" link="input" register="false" transfer="false" optional="false" type="data" size="219287440"/>
    <uses file="FFI_0_2_subfy.sgt" link="input" register="false" transfer="false" optional="false" type="data" size="219287440"/>
    <uses file="Seismogram_FFI_0_2_ID00066.grm" link="output" register="false" transfer="false" optional="false" type="data" size="24000"/>
  </job>
  <job id="ID00067" namespace="CyberShake" name="PeakValCalcOkaya" version="1.0" runtime="0.61">
    <uses file="Seismogram_FFI_0_2_ID00066.grm" link="input" register="false" transfer="false" optional="false" type="data" size="24000"/>
    <uses file="PeakVals_FFI_0_2_ID00066.bsa" link="output" register="false" transfer="false" optional="false" type="data" size="216"/>
  </job>
  <job id="ID00068" namespace="CyberShake" name="SeismogramSynthesis" version="1.0" runtime="23.02">
    <uses file="FFI_0_2_txt.variation-s06799-h07438" link="input" register="true" transfer="true" optional="false" type="data" size="5237642"/>
    <uses file="FFI_0_2_subfx.sgt" link="input" register="false" transfer="false" optional="false" type="data" size="136967044"/>
    <uses file="FFI_0_2_subfy.sgt" link="input" register="false" transfer="false" optional="false" type="data" size="136967044"/>
    <uses file="Seismogram_FFI_0_2_ID00068.grm" link="output" register="false" transfer="false" optional="false" type="data" size="24000"/>
  </job>
  <job id="ID00069" namespace="CyberShake" name="PeakValCalcOkaya" version="1.0" runtime="1.44">
    <uses file="Seismogram_FFI_0_2_ID00068.grm" link="input" register="false" transfer="false" optional="false" type="data" size="24000"/>
    <uses file="PeakVals_FFI_0_2_ID00068.bsa" link="output" register="false" transfer="false" optional="false" type="data" size="216"/>
  </job>
  <job id="ID00070" namespace="CyberShake" name="SeismogramSynthesis" version="1.0" runtime="26.94">
    <uses file="FFI_0_2_txt.variation-s09172-h05356" link="input" register="true" transfer="true" optional="false" type="data" size="2016250"/>
    <uses file="FFI_0_2_subfx.sgt" link="input" register="false" transfer="false" optional="false" type="data" size="235454833"/>
    <uses file="FFI_0_2_subfy.sgt" link="input" register="false" transfer="false" optional="false" type="data" size="235454833"/>
    <uses file="Seismogram_FFI_0_2_ID00070.grm" link="output" register="false" transfer="false" optional="false" type="data" size="24000"/>
  </job>
  <job id="ID00071" namespace="CyberShake" name="PeakValCalcOkaya" version="1.0" runtime="1.08">
    <uses file="Seismogram_FFI_0_2_ID00070.grm" link="input" register="false" transfer="false" optional="false" type="data" size="24000"/>
    <uses file="PeakVals_FFI_0_2_ID00070.bsa" link="output" register="false" transfer="false" optional="false" type="data" size="216"/>
  </job>
  <job id="ID00072" namespace="CyberShake" name="SeismogramSynthesis" version="1.0" runtime="63.09">
    <uses file="FFI_0_2_txt.variation-s08426-h08692" link="input" register="true" transfer="true" optional="false" type="data" size="3657272"/>
    <uses file="FFI_0_2_subfx.sgt" link="input" register="false" transfer="false" optional="false" type="data" size="152063134"/>
    <uses file="FFI_0_2_subfy.sgt" link="input" register="false" transfer="false" optional="false" type="data" size="152063134"/>
    <uses file="Seismogram_FFI_0_2_ID00072.grm" link="output" register="false" transfer="false" optional="false" type="data" size="24000"/>
  </job>
  <job id="ID00073" namespace="CyberShake" name="PeakValCalcOkaya" version="1.0" runtime="0.59">
    <uses file="Seismogram_FFI_0_2_ID00072.grm" link="input" register="false" transfer="false" optional="false" type="data" size="24000"/>
    <uses file="PeakVals_FFI_0_2_ID00072.bsa" link="output" register="false" transfer="false" optional="false" type="data" size="216"/>
  </job>
  <job id="ID00074" namespace="CyberShake" name="SeismogramSynthesis" version="1.0" runtime="22.48">
    <uses file="FFI_0_2_txt.variation-s06402-h02227" link="input" register="true" transfer="true" optional="false" type="data" size="4427133"/>
    <uses file="FFI_0_2_subfx.sgt" link="input" register="false" transfer="false" optional="false" type="data" size="129091493"/>
    <uses file="FFI_0_2_subfy.sgt" link="input" register="false" transfer="false" optional="false" type="data" size="129091493"/>
    <uses file="Seismogram_FFI_0_2_ID00074.grm" link="output" register="false" transfer="false" optional="false" type="data" size="24000"/>
  </job>
  <job id="ID00075" namespace="CyberShake" name="PeakValCalcOkaya" version="1.0" runtime="0.85">
    <uses file="Seismogram_FFI_0_2_ID00074.grm" link="input" register="false" transfer="false" optional="false" type="data" size="24000"/>
    <uses file="PeakVals_FFI_0_2_ID00074.bsa" link="output" register="false" transfer="false" optional="false" type="data" size="216"/>
  </job>
  <job id="ID00076" namespace="CyberShake" name="SeismogramSynthesis" version="1.0" runtime="43.56">
    <uses file="FFI_0_2_txt.variation-s04946-h00030" link="input" register="true" transfer="true" optional="false" type="data" size="3132935"/>
    <uses file="FFI_0_2_subfx.sgt" link="input" register="false" transfer="false" optional="false" type="data" size="123528394"/>
    <uses file="FFI_0_2_subfy.sgt" link="input" register="false" transfer="false" optional="false" type="data" size="123528394"/>
    <uses file="Seismogram_FFI_0_2_ID00076.grm" link="output" register="false" transfer="false" optional="false" type="data" size="24000"/>
  </job>
  <job id="ID00077" namespace="CyberShake" name="PeakValCalcOkaya" version="1.0" runtime="0.85">
    <uses file="Seismogram_FFI_0_2_ID00076.grm" link="input" register="false" transfer="false" optional="false" type="data" size="24000"/>
    <uses file="PeakVals_FFI_0_2_ID00076.bsa" link="output" register="false" transfer="false" optional="false" type="data" size="216"/>
  </job>
  <job id="ID00078" namespace="CyberShake" name="SeismogramSynthesis" version="1.0" runtime="48.47">
    <uses file="FFI_0_2_txt.variation-s02047-h07883" link="input" register="true" transfer="true" optional="false" type="data" size="2066807"/>
    <uses file="FFI_0_2_subfx.sgt" link="input" register="false" transfer="false" optional="false" type="data" size="124121712"/>
    <uses file="FFI_0_2_subfy.sgt" link="input" register="false" transfer="false" optional="false" type="data" size="124121712"/>
    <uses file="Seismogram_FFI_0_2_ID00078.grm" link="output" register="false" transfer="false" optional="false" type="data" size="24000"/>
  </job>
  <job id="ID00079" namespace="CyberShake" name="PeakValCalcOkaya" version="1.0" runtime="1.55">
    <uses file="Seismogram_FFI_0_2_ID00078.grm" link="input" register="false" transfer="false" optional="false" type="data" size="24000"/>
    <uses file="PeakVals_FFI_0_2_ID00078.bsa" link="output" register="false" transfer="false" optional="false" type="data" size="216"/>
  </job>
  <job id="ID00080" namespace="CyberShake" name="SeismogramSynthesis" version="1.0" runtime="35.34">
    <uses file="FFI_0_2_txt.variation-s09614-h09513" link="input" register="true" transfer="true" optional="false" type="data" size="3659562"/>
    <uses file="FFI_0_2_subfx.sgt" link="input" register="false" transfer="false" optional="false" type="data" size="223076088"/>
    <uses file="FFI_0_2_subfy.sgt" link="input" register="false" transfer="false" optional="false" type="data" size="223076088"/>
    <uses file="Seismogram_FFI_0_2_ID00080.grm" link="output" register="false" transfer="false" optional="false" type="data" size="24000"/>
  </job>
  <job id="ID00081" namespace="CyberShake" name="PeakValCalcOkaya" version="1.0" runtime="0.72">
    <uses file="Seismogram_FFI_0_2_ID00080.grm" link="input" register="false" transfer="false" optional="false" type="data" size="24000"/>
    <uses file="PeakVals_FFI_0_2_ID00080.bsa" link="output" register="false" transfer="false" optional="false" type="data" size="216"/>
  </job>
  <job id="ID00082" namespace="CyberShake" name="SeismogramSynthesis" version="1.0" runtime="21.79">
    <uses file="FFI_0_2_txt.variation-s09269-h07526" link="input" register="true" transfer="true" optional="false" type="data" size="4241406"/>
    <uses file="FFI_0_2_subfx.sgt" link="input" register="false" transfer="false" optional="false" type="data" size="244780204"/>
    <uses file="FFI_0_2_subfy.sgt" link="input" register="false" transfer="false" optional="false" type="data" size="244780204"/>
    <uses file="Seismogram_FFI_0_2_ID00082.grm" link="output" register="false" transfer="false" optional="false" type="data" size="24000"/>
  </job>
  <job id="ID00083" namespace="CyberShake" name="PeakValCalcOkaya" version="1.0" runtime="1.55">
    <uses file="Seismogram_FFI_0_2_ID00082.grm" link="input" register="false" transfer="false" optional="false" type="data" size="24000"/>
    <uses file="PeakVals_FFI_0_2_ID00082.bsa" link="output" register="false" transfer="false" optional="false" type="data" size="216"/>
  </job>
  <job id="ID00084" namespace="CyberShake" name="SeismogramSynthesis" version="1.0" runtime="62.64">
    <uses file="FFI_0_2_txt.variation-s03936-h06688" link="input" register="true" transfer="true" optional="false" type="data" size="5174800"/>
    <uses file="FFI_0_2_subfx.sgt" link="input" register="false" transfer="false" optional="false" type="data" size="306065932"/>
    <uses file="FFI_0_2_subfy.sgt" link="input" register="false" transfer="false" optional="false" type="data" size="306065932"/>
    <uses file="Seismogram_FFI_0_2_ID00084.grm" link="output" register="false" transfer="false" optional="false" type="data" size="24000"/>
  </job>
  <job id="ID00085" namespace="CyberShake" name="PeakValCalcOkaya" version="1.0" runtime="0.65">
    <uses file="Seismogram_FFI_0_2_ID00084.grm" link="input" register="false" transfer="false" optional="false" type="data" size="24000"/>
    <uses file="PeakVals_FFI_0_2_ID00084.bsa" link="output" register="false" transfer="false" optional="false" type="data" size="216"/>
  </job>
  <job id="ID00086" namespace="CyberShake" name="SeismogramSynthesis" version="1.0" runtime="58.81">
    <uses file="FFI_0_2_txt.variation-s09258-h06967" link="input" register="true" transfer="true" optional="false" type="data" size="4547692"/>
    <uses file="FFI_0_2_subfx.sgt" link="input" register="false" transfer="false" optional="false" type="data" size="279687848"/>
    <uses file="FFI_0_2_subfy.sgt" link="input" register="false" transfer="false" optional="false" type="data" size="279687848"/>
    <uses file="Seismogram_FFI_0_2_ID00086.grm" link="output" register="false" transfer="false" optional="false" type="data" size="24000"/>
  </job>
  <job id="ID00087" namespace="CyberShake" name="PeakValCalcOkaya" version="1.0" runtime="1.49">
    <uses file="Seismogram_FFI_0_2_ID00086.grm" link="input" register="false" transfer="false" optional="false" type="data" size="24000"/>
    <uses file="PeakVals_FFI_0_2_ID00086.bsa" link="output" register="false" transfer="false" optional="false" type="data" size="216"/>
  </job>
  <job id="ID00088" namespace="CyberShake" name="SeismogramSynthesis" version="1.0" runtime="55.66">
    <uses file="FFI_0_2_txt.variation-s06184-h05000" link="input" register="true" transfer="true" optional="false" type="data" size="4713544"/>
    <uses file="FFI_0_2_subfx.sgt" link="input" register="false" transfer="false" optional="false" type="data" size="281240757"/>
    <uses file="FFI_0_2_subfy.sgt" link="input" register="false" transfer="false" optional="false" type="data" size="281240757"/>
    <uses file="Seismogram_FFI_0_2_ID00088.grm" link="output" register="false" transfer="false" optional="false" type="data" size="24000"/>
  </job>
  <job id="ID00089" namespace="CyberShake" name="PeakValCalcOkaya" version="1.0" runtime="0.71">
    <uses file="Seismogram_FFI_0_2_ID00088.grm" link="input" register="false" transfer="false" optional="false" type="data" size="24000"/>
    <uses file="PeakVals_FFI_0_2_ID00088.bsa" link="output" register="false" transfer="false" optional="false" type="data" size="216"/>
  </job>
  <job id="ID00090" namespace="CyberShake" name="SeismogramSynthesis" version="1.0" runtime="27.64">
    <uses file="FFI_0_2_txt.variation-s05030-h08343" link="input" register="true" transfer="true" optional="false" type="data" size="4262213"/>
    <uses file="FFI_0_2_subfx.sgt" link="input" register="false" transfer="false" optional="false" type="data" size="251187186"/>
    <uses file="FFI_0_2_subfy.sgt" link="input" register="false" transfer="false" optional="false" type="data" size="251187186"/>
    <uses file="Seismogram_FFI_0_2_ID00090.grm" link="output" register="false" transfer="false" optional="false" type="data" size="24000"/>
  </job>
  <job id="ID00091" namespace="CyberShake" name="PeakValCalcOkaya" version="1.0" runtime="1.19">
    <uses file="Seismogram_FFI_0_2_ID00090.grm" link="input" register="false" transfer="false" optional="false" type="data" size="24000"/>
    <uses file="PeakVals_FFI_0_2_ID00090.bsa" link="output" register="false" transfer="false" optional="false" type="data" size="216"/>
  </job>
  <job id="ID00092" namespace="CyberShake" name="SeismogramSynthesis" version="1.0" runtime="21.92">
    <uses file="FFI_0_2_txt.variation-s00691-h01726" link="input" register="true" transfer="true" optional="false" type="data" size="5553890"/>
    <uses file="FFI_0_2_subfx.sgt" link="input" register="false" transfer="false" optional="false" type="data" size="190792864"/>
    <uses file="FFI_0_2_subfy.sgt" link="input" register="false" transfer="false" optional="false" type="data" size="190792864"/>
    <uses file="Seismogram_FFI_0_2_ID00092.grm" link="output" register="false" transfer="false" optional="false" type="data" size="24000"/>
  </job>
  <job id="ID00093" namespace="CyberShake" name="PeakValCalcOkaya" version="1.0" runtime="1.13">
    <uses file="Seismogram_FFI_0_2_ID00092.grm" link="input" register="false" transfer="false" optional="false" type="data" size="24000"/>
    <uses file="PeakVals_FFI_0_2_ID00092.bsa" link="output" register="false" transfer="false" optional="false" type="data" size="216"/>
  </job>
  <job id="ID00094" namespace="CyberShake" name="SeismogramSynthesis" version="1.0" runtime="45.25">
    <uses file="FFI_0_2_txt.variation-s06145-h00281" link="input" register="true" transfer="true" optional="false" type="data" size="3072119"/>
    <uses file="FFI_0_2_subfx.sgt" link="input" register="false" transfer="false" optional="false" type="data" size="256169680"/>
    <uses file="FFI_0_2_subfy.sgt" link="input" register="false" transfer="false" optional="false" type="data" size="256169680"/>
    <uses file="Seismogram_FFI_0_2_ID00094.grm" link="output" register="false" transfer="false" optional="false" type="data" size="24000"/>
  </job>
  <job id="ID00095" namespace="CyberShake" name="PeakValCalcOkaya" version="1.0" runtime="0.75">
    <uses file="Seismogram_FFI_0_2_ID00094.grm" link="input" register="false" transfer="false" optional="false" type="data" size="24000"/>
    <uses file="PeakVals_FFI_0_2_ID00094.bsa" link="output" register="false" transfer="false" optional="false" type="data" size="216"/>
  </job>
  <job id="ID00096" namespace="CyberShake" name="SeismogramSynthesis" version="1.0" runtime="42.50">
    <uses file="FFI_0_2_txt.variation-s09948-h07733" link="input" register="true" transfer="true" optional="false" type="data" size="5378773"/>
    <uses file="FFI_0_2_subfx.sgt" link="input" register="false" transfer="false" optional="false" type="data" size="189280946"/>
    <uses file="FFI_0_2_subfy.sgt" link="input" register="false" transfer="false" optional="false" type="data" size="189280946"/>
    <uses file="Seismogram_FFI_0_2_ID00096.grm" link="output" register="false" transfer="false" optional="false" type="data" size="24000"/>
  </job>
  <job id="ID00097" namespace="CyberShake" name="PeakValCalcOkaya" version="1.0" runtime="0.89">
    <uses file="Seismogram_FFI_0_2_ID00096.grm" link="input" register="false" transfer="false" optional="false" type="data" size="24000"/>
    <uses file="PeakVals_FFI_0_2_ID00096.bsa" link="output" register="false" transfer="false" optional="false" type="data" size="216"/>
  </job>
  <job id="ID00098" namespace="CyberShake" name="SeismogramSynthesis" version="1.0" runtime="49.80">
    <uses file="FFI_0_2_txt.variation-s00186-h01843" link="input" register="true" transfer="true" optional="false" type="data" size="2326255"/>
    <uses file="FFI_0_2_subfx.sgt" link="input" register="false" transfer="false" optional="false" type="data" size="247823434"/>
    <uses file="FFI_0_2_subfy.sgt" link="input" register="false" transfer="false" optional="false" type="data" size="247823434"/>
    <uses file="Seismogram_FFI_0_2_ID00098.grm" link="output" register="false" transfer="false" optional="false" type="data" size="24000"/>
  </job>
  <job id="ID00099" namespace="CyberShake" name="PeakValCalcOkaya" version="1.0" runtime="0.59">
    <uses file="Seismogram_FFI_0_2_ID00098.grm" link="input" register="false" transfer="false" optional="false" type="data" size="24000"/>
    <uses file="PeakVals_FFI_0_2_ID00098.bsa" link="output" register="false" transfer="false" optional="false" type="data" size="216"/>
  </job>
<!-- part 3: list of control-flow dependencies (may be empty) -->
  <child ref="ID00000">
    <parent ref="ID00095"/>
    <parent ref="ID00071"/>
    <parent ref="ID00097"/>
    <parent ref="ID00099"/>
    <parent ref="ID00006"/>
    <parent ref="ID00004"/>
    <parent ref="ID00008"/>
    <parent ref="ID00034"/>
    <parent ref="ID00059"/>
    <parent ref="ID00032"/>
    <parent ref="ID00012"/>
    <parent ref="ID00030"/>
    <parent ref="ID00010"/>
    <parent ref="ID00079"/>
    <parent ref="ID00053"/>
    <parent ref="ID00016"/>
    <parent ref="ID00077"/>
    <parent ref="ID00014"/>
    <parent ref="ID00051"/>
    <parent ref="ID00091"/>
    <parent ref="ID00075"/>
    <parent ref="ID00057"/>
    <parent ref="ID00038"/>
    <parent ref="ID00093"/>
    <parent ref="ID00073"/>
    <parent ref="ID00055"/>
    <parent ref="ID00018"/>
    <parent ref="ID00036"/>
    <parent ref="ID00081"/>
    <parent ref="ID00069"/>
    <parent ref="ID00044"/>
    <parent ref="ID00020"/>
    <parent ref="ID00046"/>
    <parent ref="ID00022"/>
    <parent ref="ID00040"/>
    <parent ref="ID00024"/>
    <parent ref="ID00042"/>
    <parent ref="ID00087"/>
    <parent ref="ID00061"/>
    <parent ref="ID00026"/>
    <parent ref="ID00089"/>
    <parent ref="ID00063"/>
    <parent ref="ID00028"/>
    <parent ref="ID00083"/>
    <parent ref="ID00065"/>
    <parent ref="ID00049"/>
    <parent ref="ID00085"/>
    <parent ref="ID00067"/>
  </child>
  <child ref="ID00001">
    <parent ref="ID00094"/>
    <parent ref="ID00070"/>
    <parent ref="ID00096"/>
    <parent ref="ID00098"/>
    <parent ref="ID00005"/>
    <parent ref="ID00003"/>
    <parent ref="ID00009"/>
    <parent ref="ID00007"/>
    <parent ref="ID00035"/>
    <parent ref="ID00058"/>
    <parent ref="ID00033"/>
    <parent ref="ID00013"/>
    <parent ref="ID00031"/>
    <parent ref="ID00011"/>
    <parent ref="ID00078"/>
    <parent ref="ID00052"/>
    <parent ref="ID00017"/>
    <parent ref="ID00076"/>
    <parent ref="ID00015"/>
    <parent ref="ID00050"/>
    <parent ref="ID00090"/>
    <parent ref="ID00074"/>
    <parent ref="ID00056"/>
    <parent ref="ID00039"/>
    <parent ref="ID00092"/>
    <parent ref="ID00072"/>
    <parent ref="ID00054"/>
    <parent ref="ID00019"/>
    <parent ref="ID00037"/>
    <parent ref="ID00080"/>
    <parent ref="ID00082"/>
    <parent ref="ID00060"/>
    <parent ref="ID00043"/>
    <parent ref="ID00045"/>
    <parent ref="ID00021"/>
    <parent ref="ID00023"/>
    <parent ref="ID00041"/>
    <parent ref="ID00088"/>
    <parent ref="ID00062"/>
    <parent ref="ID00025"/>
    <parent ref="ID00064"/>
    <parent ref="ID00027"/>
    <parent ref="ID00084"/>
    <parent ref="ID00066"/>
    <parent ref="ID00029"/>
    <parent ref="ID00048"/>
    <parent ref="ID00086"/>
    <parent ref="ID00068"/>
  </child>
  <child ref="ID00003">
    <parent ref="ID00002"/>
  </child>
  <child ref="ID00004">
    <parent ref="ID00003"/>
  </child>
  <child ref="ID00005">
    <parent ref="ID00002"/>
  </child>
  <child ref="ID00006">
    <parent ref="ID00005"/>
  </child>
  <child ref="ID00007">
    <parent ref="ID00002"/>
  </child>
  <child ref="ID00008">
    <parent ref="ID00007"/>
  </child>
  <child ref="ID00009">
    <parent ref="ID00002"/>
  </child>
  <child ref="ID00010">
    <parent ref="ID00009"/>
  </child>
  <child ref="ID00011">
    <parent ref="ID00002"/>
  </child>
  <child ref="ID00012">
    <parent ref="ID00011"/>
  </child>
  <child ref="ID00013">
    <parent ref="ID00002"/>
  </child>
  <child ref="ID00014">
    <parent ref="ID00013"/>
  </child>
  <child ref="ID00015">
    <parent ref="ID00002"/>
  </child>
  <child ref="ID00016">
    <parent ref="ID00015"/>
  </child>
  <child ref="ID00017">
    <parent ref="ID00002"/>
  </child>
  <child ref="ID00018">
    <parent ref="ID00017"/>
  </child>
  <child ref="ID00019">
    <parent ref="ID00002"/>
  </child>
  <child ref="ID00020">
    <parent ref="ID00019"/>
  </child>
  <child ref="ID00021">
    <parent ref="ID00002"/>
  </child>
  <child ref="ID00022">
    <parent ref="ID00021"/>
  </child>
  <child ref="ID00023">
    <parent ref="ID00002"/>
  </child>
  <child ref="ID00024">
    <parent ref="ID00023"/>
  </child>
  <child ref="ID00025">
    <parent ref="ID00002"/>
  </child>
  <child ref="ID00026">
    <parent ref="ID00025"/>
  </child>
  <child ref="ID00027">
    <parent ref="ID00002"/>
  </child>
  <child ref="ID00028">
    <parent ref="ID00027"/>
  </child>
  <child ref="ID00029">
    <parent ref="ID00002"/>
  </child>
  <child ref="ID00030">
    <parent ref="ID00029"/>
  </child>
  <child ref="ID00031">
    <parent ref="ID00002"/>
  </child>
  <child ref="ID00032">
    <parent ref="ID00031"/>
  </child>
  <child ref="ID00033">
    <parent ref="ID00002"/>
  </child>
  <child ref="ID00034">
    <parent ref="ID00033"/>
  </child>
  <child ref="ID00035">
    <parent ref="ID00002"/>
  </child>
  <child ref="ID00036">
    <parent ref="ID00035"/>
  </child>
  <child ref="ID00037">
    <parent ref="ID00002"/>
  </child>
  <child ref="ID00038">
    <parent ref="ID00037"/>
  </child>
  <child ref="ID00039">
    <parent ref="ID00002"/>
  </child>
  <child ref="ID00040">
    <parent ref="ID00039"/>
  </child>
  <child ref="ID00041">
    <parent ref="ID00002"/>
  </child>
  <child ref="ID00042">
    <parent ref="ID00041"/>
  </child>
  <child ref="ID00043">
    <parent ref="ID00002"/>
  </child>
  <child ref="ID00044">
    <parent ref="ID00043"/>
  </child>
  <child ref="ID00045">
    <parent ref="ID00002"/>
  </child>
  <child ref="ID00046">
    <parent ref="ID00045"/>
  </child>
  <child ref="ID00048">
    <parent ref="ID00047"/>
  </child>
  <child ref="ID00049">
    <parent ref="ID00048"/>
  </child>
  <child ref="ID00050">
    <parent ref="ID00047"/>
  </child>
  <child ref="ID00051">
    <parent ref="ID00050"/>
  </child>
  <child ref="ID00052">
    <parent ref="ID00047"/>
  </child>
  <child ref="ID00053">
    <parent ref="ID00052"/>
  </child>
  <child ref="ID00054">
    <parent ref="ID00047"/>
  </child>
  <child ref="ID00055">
    <parent ref="ID00054"/>
  </child>
  <child ref="ID00056">
    <parent ref="ID00047"/>
  </child>
  <child ref="ID00057">
    <parent ref="ID00056"/>
  </child>
  <child ref="ID00058">
    <parent ref="ID00047"/>
  </child>
  <child ref="ID00059">
    <parent ref="ID00058"/>
  </child>
  <child ref="ID00060">
    <parent ref="ID00047"/>
  </child>
  <child ref="ID00061">
    <parent ref="ID00060"/>
  </child>
  <child ref="ID00062">
    <parent ref="ID00047"/>
  </child>
  <child ref="ID00063">
    <parent ref="ID00062"/>
  </child>
  <child ref="ID00064">
    <parent ref="ID00047"/>
  </child>
  <child ref="ID00065">
    <parent ref="ID00064"/>
  </child>
  <child ref="ID00066">
    <parent ref="ID00047"/>
  </child>
  <child ref="ID00067">
    <parent ref="ID00066"/>
  </child>
  <child ref="ID00068">
    <parent ref="ID00047"/>
  </child>
  <child ref="ID00069">
    <parent ref="ID00068"/>
  </child>
  <child ref="ID00070">
    <parent ref="ID00047"/>
  </child>
  <child ref="ID00071">
    <parent ref="ID00070"/>
  </child>
  <child ref="ID00072">
    <parent ref="ID00047"/>
  </child>
  <child ref="ID00073">
    <parent ref="ID00072"/>
  </child>
  <child ref="ID00074">
    <parent ref="ID00047"/>
  </child>
  <child ref="ID00075">
    <parent ref="ID00074"/>
  </child>
  <child ref="ID00076">
    <parent ref="ID00047"/>
  </child>
  <child ref="ID00077">
    <parent ref="ID00076"/>
  </child>
  <child ref="ID00078">
    <parent ref="ID00047"/>
  </child>
  <child ref="ID00079">
    <parent ref="ID00078"/>
  </child>
  <child ref="ID00080">
    <parent ref="ID00047"/>
  </child>
  <child ref="ID00081">
    <parent ref="ID00080"/>
  </child>
  <child ref="ID00082">
    <parent ref="ID00047"/>
  </child>
  <child ref="ID00083">
    <parent ref="ID00082"/>
  </child>
  <child ref="ID00084">
    <parent ref="ID00047"/>
  </child>
  <child ref="ID00085">
    <parent ref="ID00084"/>
  </child>
  <child ref="ID00086">
    <parent ref="ID00047"/>
  </child>
  <child ref="ID00087">
    <parent ref="ID00086"/>
  </child>
  <child ref="ID00088">
    <parent ref="ID00047"/>
  </child>
  <child ref="ID00089">
    <parent ref="ID00088"/>
  </child>
  <child ref="ID00090">
    <parent ref="ID00047"/>
  </child>
  <child ref="ID00091">
    <parent ref="ID00090"/>
  </child>
  <child ref="ID00092">
    <parent ref="ID00047"/>
  </child>
  <child ref="ID00093">
    <parent ref="ID00092"/>
  </child>
  <child ref="ID00094">
    <parent ref="ID00047"/>
  </child>
  <child ref="ID00095">
    <parent ref="ID00094"/>
  </child>
  <child ref="ID00096">
    <parent ref="ID00047"/>
  </child>
  <child ref="ID00097">
    <parent ref="ID00096"/>
  </child>
  <child ref="ID00098">
    <parent ref="ID00047"/>
  </child>
  <child ref="ID00099">
    <parent ref="ID00098"/>
  </child>
</adag>
